hexo_inpainting/__init__.py
hexo_inpainting/const.py
hexo_inpainting/helper.py
hexo_inpainting/inpainting.py
hexo_inpainting/model_manager.py
hexo_inpainting/outpainting.py
hexo_inpainting/schema.py
hexo_inpainting/model/__init__.py
hexo_inpainting/model/base.py
hexo_inpainting/model/const.py
hexo_inpainting/model/controlnet.py
hexo_inpainting/model/ddim_sampler.py
hexo_inpainting/model/fcf.py
hexo_inpainting/model/helper.py
hexo_inpainting/model/instruct_pix2pix.py
hexo_inpainting/model/lama.py
hexo_inpainting/model/ldm.py
hexo_inpainting/model/manga.py
hexo_inpainting/model/mat.py
hexo_inpainting/model/opencv2.py
hexo_inpainting/model/paint_by_example.py
hexo_inpainting/model/plms_sampler.py
hexo_inpainting/model/schema.py
hexo_inpainting/model/sd.py
hexo_inpainting/model/utils.py
hexo_inpainting/model/zits.py
hexo_inpainting/model/pipeline/__init__.py
hexo_inpainting/model/pipeline/pipeline_stable_diffusion_controlnet_inpaint.py
hexo_inpainting-1.0.6.dist-info/METADATA
hexo_inpainting-1.0.6.dist-info/WHEEL
hexo_inpainting-1.0.6.dist-info/top_level.txt
hexo_inpainting-1.0.6.dist-info/RECORD
