Metadata-Version: 2.1
Name: hexo-inpainting
Version: 1.0.6
Summary: This is an image editing tool
Author: Hexo.ai
Author-email: saurabh@hexo.ai
Classifier: Programming Language :: Python :: 3
Classifier: License :: OSI Approved :: MIT License
Classifier: Operating System :: OS Independent
Requires-Dist: torch (>=1.9.0)
Requires-Dist: opencv-python
Requires-Dist: flask (==2.2.3)
Requires-Dist: flask-cors
Requires-Dist: flaskwebgui (==0.3.5)
Requires-Dist: pydantic
Requires-Dist: rich
Requires-Dist: loguru
Requires-Dist: yacs
Requires-Dist: diffusers[torch] (==0.14.0)
Requires-Dist: transformers (==4.27.4)
Requires-Dist: gradio
Requires-Dist: piexif (==1.1.3)
Requires-Dist: safetensors
Requires-Dist: omegaconf
Requires-Dist: webuiapi
